{
  "project_info": {
    "project_number": "642931615097",
    "firebase_url": "https://carspace-alpha.firebaseio.com",
    "project_id": "carspace-alpha",
    "storage_bucket": "carspace-alpha.appspot.com"
  },
  "client": [
    {
      "client_info": {
        "mobilesdk_app_id": "1:642931615097:android:73b0261dbea07f63807ba8",
        "android_client_info": {
          "package_name": "tech.zdgph.carspace"
        }
      },
      "oauth_client": [
        {
          "client_id": "642931615097-rid8f5h92tuc8870636npp1tcs5mlhm4.apps.googleusercontent.com",
          "client_type": 3
        }
      ],
      "api_key": [
        {
          "current_key": "AIzaSyATBKvXnZydsfNs8YaB7Kyb96-UDAkGujo"
        }
      ],
      "services": {
        "appinvite_service": {
          "other_platform_oauth_client": [
            {
              "client_id": "642931615097-rid8f5h92tuc8870636npp1tcs5mlhm4.apps.googleusercontent.com",
              "client_type": 3
            },
            {
              "client_id": "642931615097-3h4so80qr55p5dt8f82hjrvvs7q0gc6o.apps.googleusercontent.com",
              "client_type": 2,
              "ios_info": {
                "bundle_id": "tech.zdgph.carspace"
              }
            }
          ]
        }
      }
    }
  ],
  "configuration_version": "1"
}